README.md
setup.py
sonopy.py
sonopy.egg-info/PKG-INFO
sonopy.egg-info/SOURCES.txt
sonopy.egg-info/dependency_links.txt
sonopy.egg-info/requires.txt
sonopy.egg-info/top_level.txt