Metadata-Version: 2.1
Name: sonopy
Version: 0.1.2
Summary: A simple audio feature extraction library
Home-page: https://github.com/mycroftai/sonopy
Author: Mycroft AI
Author-email: support@mycroft.ai
Maintainer: Matthew Scholefield
Maintainer-email: matthew331199@gmail.com
License: UNKNOWN
Platform: UNKNOWN
Provides-Extra: example
Provides-Extra: comparison
